{"contents":[[{"data":""},{"data":"Cape Feare ( Sideshow Bob Returns )"},{"data":""},{"data":"Jon Vitti"},{"data":""},{"data":""}],[{"data":""},{"data":"Rosebud"},{"data":""},{"data":"John Swartzwelder"},{"data":""},{"data":""}],[{"data":""},{"data":"Homer Goes to College"},{"data":""},{"data":"Conan O&apos;Brien"},{"data":""},{"data":""}],[{"data":""},{"data":"Marge on the Lam"},{"data":""},{"data":"Bill Canterbury"},{"data":""},{"data":""}],[{"data":""},{"data":"Count Burns"},{"data":""},{"data":"Bill Canterbury"},{"data":""},{"data":""}],[{"data":""},{"data":"Bart&apos;s Inner Child"},{"data":""},{"data":"George Meyer"},{"data":""},{"data":""}],[{"data":""},{"data":"Boy - Scoutz &apos;N The Hood"},{"data":""},{"data":"Dan McGrath"},{"data":""},{"data":""}],[{"data":""},{"data":"The Last Temptation of Homer"},{"data":""},{"data":"Frank Mula"},{"data":""},{"data":""}],[{"data":""},{"data":"$pringfield"},{"data":""},{"data":"Bill Oakley &amp; Josh Weinstein"},{"data":""},{"data":""}],[{"data":""},{"data":"Homer the Vigilante"},{"data":""},{"data":"John Swartzwelder"},{"data":""},{"data":""}],[{"data":""},{"data":"Homer and Apu"},{"data":""},{"data":"Greg Daniels"},{"data":""},{"data":""}],[{"data":""},{"data":"Bart Gets Famous"},{"data":""},{"data":"John Swartzwelder"},{"data":""},{"data":""}],[{"data":""},{"data":"Lisa vs . Malibu Stacy"},{"data":""},{"data":"Bill Oakley &amp; Josh Weinstein"},{"data":""},{"data":""}],[{"data":""},{"data":"Deep Space Homer"},{"data":""},{"data":"David Mirkin"},{"data":""},{"data":""}],[{"data":""},{"data":"Homer Loves Flanders"},{"data":""},{"data":"David Richardson"},{"data":""},{"data":""}],[{"data":""},{"data":"Bart Gets an Elephant"},{"data":""},{"data":"John Swartzwelder"},{"data":""},{"data":""}],[{"data":""},{"data":"Burns&apos;s Heir"},{"data":""},{"data":"Jace Richdale"},{"data":""},{"data":""}],[{"data":""},{"data":"Sweet Seymour Skinner&apos;s Bad - ass Song"},{"data":""},{"data":"Bill Oakley &amp; Josh Weinstein"},{"data":""},{"data":""}],[{"data":""},{"data":"The Boy Who Knew Too Much"},{"data":""},{"data":"John Swartzwelder"},{"data":""},{"data":""}],[{"data":""},{"data":"Secrets of a Successful Marriage"},{"data":""},{"data":"Greg Daniels"},{"data":""},{"data":""}],[{"data":""},{"data":"Lady Bouvier&apos;s Lover"},{"data":""},{"data":"Bill Oakley &amp; Josh Weinstein"},{"data":""},{"data":""}]]}
