{"contents":[[{"data":"Snow White and the Seven Dwarfs"},{"data":"1937"}],[{"data":"Pinocchio"},{"data":"1940"}],[{"data":"Fantasia"},{"data":"1940"}],[{"data":"Dumbo"},{"data":"1941"}],[{"data":"The Reluctant Dragon"},{"data":"1941"}],[{"data":"Bambi"},{"data":"1942"}],[{"data":"Saludos Amigos"},{"data":"1943"}],[{"data":"Victory Through Air Power"},{"data":"1943"}],[{"data":"The Three Caballeros"},{"data":"1945"}],[{"data":"Song of the South"},{"data":"1946"}],[{"data":""},{"data":""}],[{"data":"The Adventures of Ichabod and Mr Toad"},{"data":"1949"}],[{"data":"Cinderella"},{"data":"1950"}],[{"data":""},{"data":""}],[{"data":"Alice in Wonderland"},{"data":"1951"}],[{"data":"Peter Pan"},{"data":"1953"}],[{"data":""},{"data":""}],[{"data":"Lady and the Tramp"},{"data":"1955"}],[{"data":""},{"data":""}],[{"data":"Sleeping Beauty"},{"data":"1959"}],[{"data":""},{"data":""}],[{"data":""},{"data":""}],[{"data":""},{"data":""}],[{"data":""},{"data":""}],[{"data":"One Hundred and One Dalmatians"},{"data":"1961"}],[{"data":""},{"data":""}],[{"data":""},{"data":""}],[{"data":""},{"data":""}],[{"data":""},{"data":""}],[{"data":""},{"data":""}],[{"data":"The Sword in the Stone"},{"data":"1963"}],[{"data":""},{"data":""}],[{"data":"Mary Poppins"},{"data":"1964"}]]}
