{"contents":[[{"data":""},{"data":""},{"data":""},{"data":""},{"data":""}],[{"data":""},{"data":""},{"data":""},{"data":""},{"data":""}],[{"data":""},{"data":""},{"data":""},{"data":""},{"data":""}],[{"data":""},{"data":""},{"data":""},{"data":""},{"data":""}],[{"data":""},{"data":""},{"data":""},{"data":""},{"data":""}],[{"data":""},{"data":""},{"data":""},{"data":""},{"data":""}],[{"data":""},{"data":""},{"data":""},{"data":""},{"data":""}],[{"data":""},{"data":""},{"data":""},{"data":""},{"data":""}],[{"data":""},{"data":""},{"data":""},{"data":""},{"data":""}],[{"data":""},{"data":""},{"data":""},{"data":""},{"data":""}],[{"data":""},{"data":""},{"data":""},{"data":""},{"data":""}],[{"data":""},{"data":""},{"data":"LÃ\u0083Â\u0083Ã\u0082Â©opold III"},{"data":""},{"data":"his son"}],[{"data":""},{"data":""},{"data":""},{"data":""},{"data":""}],[{"data":""},{"data":""},{"data":""},{"data":""},{"data":""}]]}
