{"contents":[[{"data":"Assateague State Park"},{"data":"Worcester County"},{"data":""},{"data":""},{"data":""}],[{"data":"Deep Creek State Park"},{"data":"Garrett County"},{"data":""},{"data":""},{"data":""}],[{"data":"Gunpowder Falls State Park"},{"data":"Baltimore County"},{"data":""},{"data":""},{"data":""}],[{"data":"Pocomoke River State Park"},{"data":"Worcester County"},{"data":""},{"data":""},{"data":""}],[{"data":"Point Lookout State Park"},{"data":"St . Mary&apos;s County"},{"data":""},{"data":""},{"data":""}],[{"data":"Rocky Gap State Park"},{"data":"Allegany County"},{"data":""},{"data":""},{"data":""}],[{"data":"St . Mary&apos;s River State Park"},{"data":"St . Mary&apos;s County"},{"data":""},{"data":""},{"data":""}],[{"data":"Seneca Creek State Park"},{"data":"Montgomery County"},{"data":""},{"data":""},{"data":""}],[{"data":"Susquehanna State Park"},{"data":"Harford County"},{"data":""},{"data":""},{"data":""}]]}
