{"relation":[["Area","Canalave City","Valley Windworks","Fuego Ironworks","Iron Island","Route 205 (South, Towards Floaroma Town)","Route 218","Route 219","Sea Route 220","Route 221"],["Levels","20-50","30-50","20-50","20-50","20-50","20-50","20-50","30-40","20-50"],["Method","Fishing with a Super Rod","Fishing with a Super Rod","Fishing with a Super Rod","Fishing with a Super Rod","Fishing with a Super Rod","Fishing with a Super Rod","Fishing with a Super Rod","Fishing with a Super Rod","Fishing with a Super Rod"],["Rarity","45%","45%","45%","45%","45%","45%","45%","15%","45%"]],"pageTitle":"Lumineon #457 (Neon Pokemon) - Pokedex :: PokeDream","title":"","url":"http://pokedream.com/pokedex/pokemon/lumineon?display\u003dfifth\u0026order\u003dasc\u0026ref\u003dfeatured\u0026sort\u003dtype1","hasHeader":true,"headerPosition":"FIRST_ROW","tableType":"RELATION","tableNum":4,"s3Link":"common-crawl/crawl-data/CC-MAIN-2015-32/segments/1438042986423.95/warc/CC-MAIN-20150728002306-00041-ip-10-236-191-2.ec2.internal.warc.gz","recordEndOffset":194746338,"recordOffset":194730747,"tableOrientation":"HORIZONTAL","textBeforeTable":"Lumineon #457 - Neon Pokemon #458 Mantyke → ← #456 Finneon Random #650 - #718 #494 - #649 #387 - #493 #252 - #386 #152 - #251 #001 - #151 More Pokemon 6th (XY) 5th (BW) 4th (DPPl) Generations Flavor Text Images Stats Egg Moves TMs/HMs Level-up Moves Abilities Locations Breeding Evolutions General Sections Lumineon #457 e9.size \u003d \u0027468x60\u0027; e9 \u003d new Object();","textAfterTable":"#457 - Lumineon Lv. 31 Breeding Egg Groups Steps to Hatch Water 2 5,100 Locations Where to catch Lumineon in Pokemon Diamond and Pearl Area Levels Method Rarity Canalave City 20-50 Fishing with a Super Rod 45% Valley Windworks 30-50 Fishing with a Super Rod 45% Fuego Ironworks 20-50 Fishing with a Super Rod 45% Iron Island 20-50 Fishing with a Super Rod 45% Route 205 (South, Towards Floaroma Town) 20-50 Fishing with a Super Rod 45% Route 218 20-50 Fishing with a Super Rod 45% Route 219 20-50 Fishing with a Super Rod 45% Sea Route 220 30-40 Fishing with a Super Rod 15% Route 221 20-50 Fishing","hasKeyColumn":true,"keyColumnIndex":0,"headerRowIndex":0}