{"relation":[["Record ID","BNF|14583398","BNE|XX1614642","LC|no2007018605","WKP|Petchtai_Wongkamlao","WKP|Mum_Jokmok","WKP|Petchtai_Wongkamlao","SUDOC|086267159","ISNI|0000000059446454","WKP|Mum_Jokmok","WKP|Q668207","DBC|87097969647170"],["Action","add","add","add","add","add","delete","add","add","delete","add","add"],["Time","2009-03-03T12:03:19+00:00","2009-06-15T11:42:47+00:00","2009-06-15T11:42:47+00:00","2012-11-26T09:56:13+00:00","2012-12-19T19:11:18+00:00","2012-12-19T19:11:18+00:00","2014-08-28T14:36:24+00:00","2014-12-15T16:26:32+00:00","2015-04-14T18:56:54+00:00","2015-04-14T18:56:54+00:00","2015-05-12T00:14:00+00:00"]],"pageTitle":"56856657","title":"","url":"http://viaf.org/viaf/56856657/","hasHeader":true,"headerPosition":"FIRST_ROW","tableType":"RELATION","tableNum":1,"s3Link":"common-crawl/crawl-data/CC-MAIN-2015-32/segments/1438042989790.89/warc/CC-MAIN-20150728002309-00256-ip-10-236-191-2.ec2.internal.warc.gz","recordEndOffset":257824091,"recordOffset":257810601,"tableOrientation":"HORIZONTAL","textBeforeTable":"History of VIAF ID:56856657 (11) Just Links in JSON RDF record VIAF Cluster in XML MARC-21 record Record Views WorldCat Identities Wikipedia - http://th.wikipedia.org/wiki/หม่ำ_จ๊กมก Wikipedia - http://ru.wikipedia.org/wiki/Петчтай_Вонгкамлао Wikipedia - http://pt.wikipedia.org/wiki/Petchtai_Wongkamlao Wikipedia - http://pl.wikipedia.org/wiki/Petchtai_Wongkamlao Wikipedia - http://nl.wikipedia.org/wiki/Petchtai_Wongkamlao Wikipedia - http://gl.wikipedia.org/wiki/Petchtai_Wongkamlao Wikipedia - http://fr.wikipedia.org/wiki/Petchtai_Wongkamlao Wikipedia - http://fi.wikipedia.org/wiki/Petchtai_Wongkamlao Wikipedia - http://es.wikipedia.org/wiki/Petchtai_Wongkamlao Wikipedia - http://en.wikipedia.org/wiki/Mum_Jokmok Wikipedia - http://de.wikipedia.org/wiki/Petchtai_Wongkamlao External Links TH - Thailand Nationality: Gender: Male","textAfterTable":"RSS feed for changes © 2010-2014 OCLC Privacy Policy Hosted by OCLC About the Dataset Send Us a Comment. About VIAF","hasKeyColumn":false,"keyColumnIndex":-1,"headerRowIndex":0}