{"relation":[["Hole","Black tee","Blue tee","White tee","Red tee","Par"],["10","444","440","417","366","4"],["11","505","490","474","458","5"],["12","152","142","123","106","3"],["13","437","410","407","331","4"],["14","222","196","180","157","3"],["15","466","457","450","401","5"],["16","374","351","337","259","4"],["17","145","134","122","114","3"],["18","470","450","424","337","4"],["In*","3215","3070","2934","2529","35"]],"pageTitle":"Tehama Golf Club in Carmel, CA | Golf course reviews \u0026 more | PGA.com","title":"Back Nine","url":"http://www.pga.com/golf-courses/details/ca/carmel/tehama-golf-club?quicktabs_1\u003d2","hasHeader":true,"headerPosition":"FIRST_ROW","tableType":"RELATION","tableNum":2,"s3Link":"common-crawl/crawl-data/CC-MAIN-2015-32/segments/1438042986423.95/warc/CC-MAIN-20150728002306-00140-ip-10-236-191-2.ec2.internal.warc.gz","recordEndOffset":646949702,"recordOffset":646933308,"tableOrientation":"HORIZONTAL","textBeforeTable":"37 5 4 4 3 4 5 3/4 4 5 Par 2604 338 328 301 125 211 427 101 330 443 Red tee 2983 380 362 383 138 251 500 112 358 499 White tee 3148 400 378 399 148 254 522 138 383 526 Blue tee 3305 408 417 407 158 280 530 146 415 544 Black tee Out* 9 8 7 6 5 4 3 2 1 Hole Front Nine 5,133 125 70.8 72 Red tee 5,917 128 69.6 72 White tee 6,218 135 71.0 74 Blue tee 6,520 138 72.4 72 Black tee Yardage Slope Rating Par Twitter – http://www.pga.com/ Regulation Length Holes – 18 Architect Name – Jay Morrish, ASGCA Course Details/History","textAfterTable":"*Par value varies depending on tee boxes used. Home » Golf Courses » California » Carmel » Tehama Golf Club Courses Nearby Del Monte Golf Course Monterey, CA (2.1 miles) Select ratingGive it 1/5Give it 2/5Give it 3/5Give it 4/5Give it 5/5 Average: 4.3 (3 votes)","hasKeyColumn":true,"keyColumnIndex":0,"headerRowIndex":0}