{"relation":[["Plot/Acting","Extras","Audio/Video Quality","Worth"],["","","","$17.00"]],"pageTitle":"3 Fucking Me Movie Review by barrettman | Adult DVD Talk | Porn Movie Shopping Guide","title":"","url":"http://www.adultdvdtalk.com/review/3-fucking-me","hasHeader":false,"headerPosition":"NONE","tableType":"LAYOUT","tableNum":4,"s3Link":"common-crawl/crawl-data/CC-MAIN-2015-32/segments/1438042981460.12/warc/CC-MAIN-20150728002301-00002-ip-10-236-191-2.ec2.internal.warc.gz","recordEndOffset":278006313,"recordOffset":277998111,"tableOrientation":"HORIZONTAL","textBeforeTable":"barrettman\u0027s ratings for 3 Fucking Me: Streaming/Download DVD Rent Where to buy: 8/1/2006 Peyton L. Allison Pierce Jeanie Marie Sullivan Missy Monroe Sandra Romain Sascha Trent Tesoro Harley Released on:  , , , , , , , ,","textAfterTable":"  Plot/Acting Extras Audio/Video Quality Worth $17.00 Rating Scale","hasKeyColumn":true,"keyColumnIndex":0,"headerRowIndex":-1}